{
  "map": "01_21_26_map2",
  "mapAfterWin": null,
  "itemCountMin": 15,
  "itemCountMax": 30,
  "goldPrize": 0,
  "itemPrizes": [
    "freezer",
    "poisonDartFrog",
    "lilypad",
    "mushroom",
    "lilypad"
  ],
  "rounds": [
    [
      {
        "count": 8,
        "delay": 1.25,
        "type": "horsefly",
        "spawn": "nest1",
        "checkpoints": null
      },
      {
        "count": 4,
        "delay": 0.97212946,
        "type": "mosquito",
        "spawn": "nest1",
        "checkpoints": null
      },
      {
        "count": 5,
        "delay": 1.25,
        "type": "horsefly",
        "spawn": "nest1",
        "checkpoints": null
      },
      {
        "count": 9,
        "delay": 1.2620559,
        "type": "mosquito",
        "spawn": "nest1",
        "checkpoints": null
      },
      {
        "count": 2,
        "delay": 1.2610372,
        "type": "mosquito",
        "spawn": "nest2",
        "checkpoints": null
      }
    ],
    [
      {
        "count": 18,
        "delay": 1.0055418,
        "type": "mosquito",
        "spawn": "nest2",
        "checkpoints": null
      },
      {
        "count": 12,
        "delay": 0.9719625,
        "type": "mosquito",
        "spawn": "nest2",
        "checkpoints": null
      },
      {
        "count": 1,
        "delay": 0.9553191,
        "type": "mosquito",
        "spawn": "nest2",
        "checkpoints": null
      }
    ],
    [
      {
        "count": 4,
        "delay": 0.94791174,
        "type": "moth",
        "spawn": "nest1",
        "checkpoints": null
      },
      {
        "count": 19,
        "delay": 0.9429342,
        "type": "mosquito",
        "spawn": "nest2",
        "checkpoints": null
      },
      {
        "count": 4,
        "delay": 0.91075176,
        "type": "mosquito",
        "spawn": "nest2",
        "checkpoints": null
      }
    ],
    [
      {
        "count": 16,
        "delay": 0.7707211,
        "type": "mosquito",
        "spawn": "nest1",
        "checkpoints": null
      },
      {
        "count": 13,
        "delay": 1.0999999,
        "type": "horsefly",
        "spawn": "nest1",
        "checkpoints": null
      },
      {
        "count": 1,
        "delay": 1.0452303,
        "type": "mosquito",
        "spawn": "nest1",
        "checkpoints": null
      }
    ],
    [
      {
        "count": 12,
        "delay": 1.05,
        "type": "horsefly",
        "spawn": "nest1",
        "checkpoints": null
      },
      {
        "count": 3,
        "delay": 1.05,
        "type": "superMosquito",
        "spawn": "nest1",
        "checkpoints": null
      },
      {
        "count": 9,
        "delay": 0.7944455,
        "type": "mosquito",
        "spawn": "nest1",
        "checkpoints": null
      },
      {
        "count": 7,
        "delay": 0.94683313,
        "type": "mosquito",
        "spawn": "nest2",
        "checkpoints": null
      },
      {
        "count": 2,
        "delay": 1.05,
        "type": "horsefly",
        "spawn": "nest1",
        "checkpoints": null
      }
    ],
    [
      {
        "count": 8,
        "delay": 0.5849999,
        "type": "wasp",
        "spawn": "nest1",
        "checkpoints": null
      },
      {
        "count": 6,
        "delay": 0.5849999,
        "type": "wasp",
        "spawn": "nest2",
        "checkpoints": null
      },
      {
        "count": 38,
        "delay": 0.5849999,
        "type": "wasp",
        "spawn": "nest1",
        "checkpoints": null
      }
    ],
    [
      {
        "count": 6,
        "delay": 0.52894634,
        "type": "mosquito",
        "spawn": "nest2",
        "checkpoints": null
      },
      {
        "count": 11,
        "delay": 0.9499999,
        "type": "horsefly",
        "spawn": "nest1",
        "checkpoints": null
      },
      {
        "count": 25,
        "delay": 0.33625025,
        "type": "mosquito",
        "spawn": "nest1",
        "checkpoints": null
      }
    ],
    [
      {
        "count": 14,
        "delay": 0.49499995,
        "type": "wasp",
        "spawn": "nest1",
        "checkpoints": null
      },
      {
        "count": 44,
        "delay": 0.49499995,
        "type": "wasp",
        "spawn": "nest2",
        "checkpoints": null
      }
    ],
    [
      {
        "count": 1,
        "delay": 0.8499999,
        "type": "wasp",
        "spawn": "nest2",
        "checkpoints": null
      },
      {
        "count": 12,
        "delay": 0.8499999,
        "type": "horsefly",
        "spawn": "nest2",
        "checkpoints": null
      },
      {
        "count": 4,
        "delay": 0.15224618,
        "type": "mosquito",
        "spawn": "nest1",
        "checkpoints": null
      },
      {
        "count": 30,
        "delay": 0.8499999,
        "type": "superMosquito",
        "spawn": "nest1",
        "checkpoints": null
      }
    ],
    [
      {
        "count": 33,
        "delay": 0.35999992,
        "type": "wasp",
        "spawn": "nest2",
        "checkpoints": null
      },
      {
        "count": 28,
        "delay": 0.35999992,
        "type": "wasp",
        "spawn": "nest1",
        "checkpoints": null
      }
    ],
    [
      {
        "count": 13,
        "delay": 0.07909429,
        "type": "mosquito",
        "spawn": "nest1",
        "checkpoints": null
      },
      {
        "count": 24,
        "delay": 0.74999994,
        "type": "horsefly",
        "spawn": "nest1",
        "checkpoints": null
      },
      {
        "count": 17,
        "delay": 0.74999994,
        "type": "superMosquito",
        "spawn": "nest1",
        "checkpoints": null
      }
    ],
    [
      {
        "count": 7,
        "delay": 0.26589656,
        "type": "mosquito",
        "spawn": "nest2",
        "checkpoints": null
      },
      {
        "count": 4,
        "delay": 0.3093052,
        "type": "moth",
        "spawn": "nest1",
        "checkpoints": null
      },
      {
        "count": 24,
        "delay": 0.6999999,
        "type": "superMosquito",
        "spawn": "nest2",
        "checkpoints": null
      },
      {
        "count": 12,
        "delay": 0.6999999,
        "type": "wasp",
        "spawn": "nest2",
        "checkpoints": null
      }
    ],
    [
      {
        "count": 18,
        "delay": 0.22499901,
        "type": "snoutFly",
        "spawn": "nest2",
        "checkpoints": null
      },
      {
        "count": 14,
        "delay": 0.6499999,
        "type": "wasp",
        "spawn": "nest1",
        "checkpoints": null
      },
      {
        "count": 15,
        "delay": 0.042717338,
        "type": "mosquito",
        "spawn": "nest1",
        "checkpoints": null
      },
      {
        "count": 10,
        "delay": 0.034017682,
        "type": "mosquito",
        "spawn": "nest2",
        "checkpoints": null
      }
    ],
    [
      {
        "count": 19,
        "delay": 0.59999996,
        "type": "wasp",
        "spawn": "nest2",
        "checkpoints": null
      },
      {
        "count": 18,
        "delay": 0.23503917,
        "type": "snoutFly",
        "spawn": "nest2",
        "checkpoints": null
      },
      {
        "count": 10,
        "delay": 0.16188884,
        "type": "moth",
        "spawn": "nest1",
        "checkpoints": null
      },
      {
        "count": 8,
        "delay": 0.59999996,
        "type": "superMosquito",
        "spawn": "nest1",
        "checkpoints": null
      },
      {
        "count": 2,
        "delay": 0.59999996,
        "type": "horsefly",
        "spawn": "nest1",
        "checkpoints": null
      },
      {
        "count": 5,
        "delay": 0.058558583,
        "type": "snoutFly",
        "spawn": "nest2",
        "checkpoints": null
      }
    ],
    [
      {
        "count": 33,
        "delay": 0.17999993,
        "type": "wasp",
        "spawn": "nest1",
        "checkpoints": null
      },
      {
        "count": 4,
        "delay": 0.17999993,
        "type": "wasp",
        "spawn": "nest2",
        "checkpoints": null
      },
      {
        "count": 37,
        "delay": 0.17999993,
        "type": "wasp",
        "spawn": "nest1",
        "checkpoints": null
      }
    ],
    [
      {
        "count": 20,
        "delay": 0.089999914,
        "type": "wasp",
        "spawn": "nest2",
        "checkpoints": null
      },
      {
        "count": 42,
        "delay": 0.089999914,
        "type": "wasp",
        "spawn": "nest1",
        "checkpoints": null
      },
      {
        "count": 23,
        "delay": 0.089999914,
        "type": "wasp",
        "spawn": "nest2",
        "checkpoints": null
      }
    ],
    [
      {
        "count": 4,
        "delay": 0.19831353,
        "type": "moth",
        "spawn": "nest1",
        "checkpoints": null
      },
      {
        "count": 46,
        "delay": 0.44999993,
        "type": "superMosquito",
        "spawn": "nest2",
        "checkpoints": null
      },
      {
        "count": 3,
        "delay": 0.23838168,
        "type": "moth",
        "spawn": "nest1",
        "checkpoints": null
      },
      {
        "count": 6,
        "delay": 0.02,
        "type": "mosquito",
        "spawn": "nest2",
        "checkpoints": null
      }
    ],
    [
      {
        "count": 42,
        "delay": 0.044999957,
        "type": "wasp",
        "spawn": "nest1",
        "checkpoints": null
      },
      {
        "count": 5,
        "delay": 0.044999957,
        "type": "wasp",
        "spawn": "nest2",
        "checkpoints": null
      },
      {
        "count": 19,
        "delay": 0.044999957,
        "type": "wasp",
        "spawn": "nest1",
        "checkpoints": null
      },
      {
        "count": 21,
        "delay": 0.044999957,
        "type": "wasp",
        "spawn": "nest2",
        "checkpoints": null
      }
    ],
    [
      {
        "count": 14,
        "delay": 0.34999996,
        "type": "horsefly",
        "spawn": "nest2",
        "checkpoints": null
      },
      {
        "count": 16,
        "delay": 0.40937325,
        "type": "moth",
        "spawn": "nest1",
        "checkpoints": null
      },
      {
        "count": 30,
        "delay": 0.34999996,
        "type": "superMosquito",
        "spawn": "nest1",
        "checkpoints": null
      },
      {
        "count": 5,
        "delay": 0.48075193,
        "type": "moth",
        "spawn": "nest1",
        "checkpoints": null
      }
    ],
    [
      {
        "count": 51,
        "delay": 0.02,
        "type": "mosquito",
        "spawn": "nest1",
        "checkpoints": null
      },
      {
        "count": 22,
        "delay": 0.29999995,
        "type": "horsefly",
        "spawn": "nest1",
        "checkpoints": null
      }
    ],
    [
      {
        "count": 10,
        "delay": 0.24999988,
        "type": "superMosquito",
        "spawn": "nest1",
        "checkpoints": null
      },
      {
        "count": 22,
        "delay": 0.27448553,
        "type": "moth",
        "spawn": "nest1",
        "checkpoints": null
      },
      {
        "count": 15,
        "delay": 0.29803914,
        "type": "snoutFly",
        "spawn": "nest2",
        "checkpoints": null
      },
      {
        "count": 17,
        "delay": 0.24999988,
        "type": "wasp",
        "spawn": "nest2",
        "checkpoints": null
      },
      {
        "count": 7,
        "delay": 0.24999988,
        "type": "wasp",
        "spawn": "nest1",
        "checkpoints": null
      },
      {
        "count": 7,
        "delay": 1.1367674,
        "type": "superMoth",
        "spawn": "nest1",
        "checkpoints": null
      }
    ],
    [
      {
        "count": 42,
        "delay": 0.19999993,
        "type": "superMosquito",
        "spawn": "nest1",
        "checkpoints": null
      },
      {
        "count": 20,
        "delay": 0.74787915,
        "type": "superMoth",
        "spawn": "nest2",
        "checkpoints": null
      },
      {
        "count": 8,
        "delay": 0.19999993,
        "type": "superMosquito",
        "spawn": "nest2",
        "checkpoints": null
      }
    ],
    [
      {
        "count": 69,
        "delay": 0.018,
        "type": "wasp",
        "spawn": "nest1",
        "checkpoints": null
      },
      {
        "count": 29,
        "delay": 0.018,
        "type": "wasp",
        "spawn": "nest2",
        "checkpoints": null
      }
    ],
    [
      {
        "count": 2,
        "delay": 0.099999905,
        "type": "superMosquito",
        "spawn": "nest2",
        "checkpoints": null
      },
      {
        "count": 12,
        "delay": 0.099999905,
        "type": "wasp",
        "spawn": "nest2",
        "checkpoints": null
      },
      {
        "count": 10,
        "delay": 0.8685349,
        "type": "superMoth",
        "spawn": "nest1",
        "checkpoints": null
      },
      {
        "count": 6,
        "delay": 0.37684852,
        "type": "moth",
        "spawn": "nest2",
        "checkpoints": null
      },
      {
        "count": 26,
        "delay": 0.099999905,
        "type": "superMosquito",
        "spawn": "nest2",
        "checkpoints": null
      },
      {
        "count": 21,
        "delay": 0.057148695,
        "type": "moth",
        "spawn": "nest2",
        "checkpoints": null
      },
      {
        "count": 4,
        "delay": 0.9646059,
        "type": "superMoth",
        "spawn": "nest1",
        "checkpoints": null
      },
      {
        "count": 3,
        "delay": 0.87288797,
        "type": "superMoth",
        "spawn": "nest1",
        "checkpoints": null
      }
    ],
    [
      {
        "count": 62,
        "delay": 0.018,
        "type": "wasp",
        "spawn": "nest1",
        "checkpoints": null
      },
      {
        "count": 25,
        "delay": 0.018,
        "type": "wasp",
        "spawn": "nest2",
        "checkpoints": null
      },
      {
        "count": 10,
        "delay": 0.018,
        "type": "wasp",
        "spawn": "nest1",
        "checkpoints": null
      }
    ],
    [
      {
        "count": 28,
        "delay": 0.24303156,
        "type": "snoutFly",
        "spawn": "nest1",
        "checkpoints": null
      },
      {
        "count": 7,
        "delay": 0.21154898,
        "type": "snoutFly",
        "spawn": "nest2",
        "checkpoints": null
      },
      {
        "count": 16,
        "delay": 0.18782312,
        "type": "snoutFly",
        "spawn": "nest2",
        "checkpoints": null
      },
      {
        "count": 35,
        "delay": 0.02,
        "type": "superMosquito",
        "spawn": "nest2",
        "checkpoints": null
      }
    ],
    [
      {
        "count": 22,
        "delay": 0.2775625,
        "type": "snoutFly",
        "spawn": "nest1",
        "checkpoints": null
      },
      {
        "count": 40,
        "delay": 0.02,
        "type": "wasp",
        "spawn": "nest2",
        "checkpoints": null
      },
      {
        "count": 7,
        "delay": 0.02,
        "type": "superMosquito",
        "spawn": "nest1",
        "checkpoints": null
      },
      {
        "count": 1,
        "delay": 0.13766032,
        "type": "moth",
        "spawn": "nest2",
        "checkpoints": null
      },
      {
        "count": 13,
        "delay": 0.78921574,
        "type": "superMoth",
        "spawn": "nest2",
        "checkpoints": null
      },
      {
        "count": 2,
        "delay": 0.28095508,
        "type": "moth",
        "spawn": "nest2",
        "checkpoints": null
      }
    ],
    [
      {
        "count": 30,
        "delay": 0.4405028,
        "type": "snoutFly",
        "spawn": "nest1",
        "checkpoints": null
      },
      {
        "count": 59,
        "delay": 0.02,
        "type": "superMosquito",
        "spawn": "nest1",
        "checkpoints": null
      }
    ],
    [
      {
        "count": 25,
        "delay": 0.06804943,
        "type": "moth",
        "spawn": "nest1",
        "checkpoints": null
      },
      {
        "count": 32,
        "delay": 0.44987142,
        "type": "snoutFly",
        "spawn": "nest1",
        "checkpoints": null
      },
      {
        "count": 1,
        "delay": 0.2458142,
        "type": "moth",
        "spawn": "nest2",
        "checkpoints": null
      },
      {
        "count": 26,
        "delay": 0.05646503,
        "type": "moth",
        "spawn": "nest1",
        "checkpoints": null
      },
      {
        "count": 2,
        "delay": 0.6568799,
        "type": "superMoth",
        "spawn": "nest2",
        "checkpoints": null
      }
    ],
    [
      {
        "count": 19,
        "delay": 0.1909867,
        "type": "moth",
        "spawn": "nest2",
        "checkpoints": null
      },
      {
        "count": 33,
        "delay": 0.02,
        "type": "superMosquito",
        "spawn": "nest2",
        "checkpoints": null
      },
      {
        "count": 1,
        "delay": 0.679721,
        "type": "superMoth",
        "spawn": "nest2",
        "checkpoints": null
      },
      {
        "count": 3,
        "delay": 0.3979231,
        "type": "snoutFly",
        "spawn": "nest2",
        "checkpoints": null
      },
      {
        "count": 23,
        "delay": 0.02,
        "type": "wasp",
        "spawn": "nest2",
        "checkpoints": null
      },
      {
        "count": 13,
        "delay": 0.19517702,
        "type": "moth",
        "spawn": "nest2",
        "checkpoints": null
      },
      {
        "count": 7,
        "delay": 0.02,
        "type": "superMosquito",
        "spawn": "nest2",
        "checkpoints": null
      }
    ],
    [
      {
        "count": 24,
        "delay": 0.64201164,
        "type": "superMoth",
        "spawn": "nest2",
        "checkpoints": null
      },
      {
        "count": 6,
        "delay": 0.4851791,
        "type": "moth",
        "spawn": "nest2",
        "checkpoints": null
      },
      {
        "count": 24,
        "delay": 0.20525867,
        "type": "moth",
        "spawn": "nest1",
        "checkpoints": null
      },
      {
        "count": 29,
        "delay": 0.11217111,
        "type": "moth",
        "spawn": "nest1",
        "checkpoints": null
      },
      {
        "count": 10,
        "delay": 0.02,
        "type": "wasp",
        "spawn": "nest1",
        "checkpoints": null
      }
    ],
    [
      {
        "count": 10,
        "delay": 0.48020518,
        "type": "superMoth",
        "spawn": "nest1",
        "checkpoints": null
      },
      {
        "count": 5,
        "delay": 0.24514359,
        "type": "snoutFly",
        "spawn": "nest2",
        "checkpoints": null
      },
      {
        "count": 42,
        "delay": 0.02,
        "type": "superMosquito",
        "spawn": "nest1",
        "checkpoints": null
      },
      {
        "count": 44,
        "delay": 0.02,
        "type": "wasp",
        "spawn": "nest2",
        "checkpoints": null
      }
    ],
    [
      {
        "count": 21,
        "delay": 0.4021144,
        "type": "superMoth",
        "spawn": "nest2",
        "checkpoints": null
      },
      {
        "count": 2,
        "delay": 0.02,
        "type": "superMosquito",
        "spawn": "nest1",
        "checkpoints": null
      },
      {
        "count": 31,
        "delay": 0.42181242,
        "type": "snoutFly",
        "spawn": "nest1",
        "checkpoints": null
      },
      {
        "count": 27,
        "delay": 0.02,
        "type": "wasp",
        "spawn": "nest1",
        "checkpoints": null
      },
      {
        "count": 18,
        "delay": 0.35712802,
        "type": "snoutFly",
        "spawn": "nest2",
        "checkpoints": null
      }
    ],
    [
      {
        "count": 50,
        "delay": 0.018,
        "type": "wasp",
        "spawn": "nest2",
        "checkpoints": null
      },
      {
        "count": 49,
        "delay": 0.018,
        "type": "wasp",
        "spawn": "nest1",
        "checkpoints": null
      },
      {
        "count": 12,
        "delay": 0.018,
        "type": "wasp",
        "spawn": "nest2",
        "checkpoints": null
      },
      {
        "count": 5,
        "delay": 0.018,
        "type": "wasp",
        "spawn": "nest1",
        "checkpoints": null
      }
    ],
    [
      {
        "count": 28,
        "delay": 0.09718704,
        "type": "moth",
        "spawn": "nest1",
        "checkpoints": null
      },
      {
        "count": 72,
        "delay": 0.02,
        "type": "superMosquito",
        "spawn": "nest1",
        "checkpoints": null
      }
    ],
    [
      {
        "count": 53,
        "delay": 0.018,
        "type": "wasp",
        "spawn": "nest1",
        "checkpoints": null
      },
      {
        "count": 70,
        "delay": 0.018,
        "type": "wasp",
        "spawn": "nest2",
        "checkpoints": null
      }
    ],
    [
      {
        "count": 23,
        "delay": 0.25501573,
        "type": "superMoth",
        "spawn": "nest2",
        "checkpoints": null
      },
      {
        "count": 16,
        "delay": 0.3179677,
        "type": "snoutFly",
        "spawn": "nest2",
        "checkpoints": null
      },
      {
        "count": 7,
        "delay": 0.2540598,
        "type": "snoutFly",
        "spawn": "nest2",
        "checkpoints": null
      },
      {
        "count": 34,
        "delay": 0.43759346,
        "type": "superMoth",
        "spawn": "nest1",
        "checkpoints": null
      },
      {
        "count": 18,
        "delay": 0.02,
        "type": "superMosquito",
        "spawn": "nest1",
        "checkpoints": null
      },
      {
        "count": 7,
        "delay": 0.02,
        "type": "wasp",
        "spawn": "nest2",
        "checkpoints": null
      }
    ],
    [
      {
        "count": 27,
        "delay": 0.02,
        "type": "superMosquito",
        "spawn": "nest2",
        "checkpoints": null
      },
      {
        "count": 50,
        "delay": 0.12425852,
        "type": "snoutFly",
        "spawn": "nest2",
        "checkpoints": null
      },
      {
        "count": 22,
        "delay": 0.40538633,
        "type": "superMoth",
        "spawn": "nest2",
        "checkpoints": null
      },
      {
        "count": 15,
        "delay": 0.30739266,
        "type": "snoutFly",
        "spawn": "nest2",
        "checkpoints": null
      }
    ],
    [
      {
        "count": 42,
        "delay": 0.11036849,
        "type": "snoutFly",
        "spawn": "nest1",
        "checkpoints": null
      },
      {
        "count": 29,
        "delay": 0.32538956,
        "type": "superMoth",
        "spawn": "nest2",
        "checkpoints": null
      },
      {
        "count": 3,
        "delay": 0.42592597,
        "type": "snoutFly",
        "spawn": "nest2",
        "checkpoints": null
      },
      {
        "count": 45,
        "delay": 0.25308603,
        "type": "snoutFly",
        "spawn": "nest2",
        "checkpoints": null
      }
    ],
    [
      {
        "count": 38,
        "delay": 0.34573162,
        "type": "superMoth",
        "spawn": "nest1",
        "checkpoints": null
      },
      {
        "count": 14,
        "delay": 0.38748753,
        "type": "moth",
        "spawn": "nest2",
        "checkpoints": null
      },
      {
        "count": 19,
        "delay": 0.16627616,
        "type": "superMoth",
        "spawn": "nest2",
        "checkpoints": null
      },
      {
        "count": 15,
        "delay": 0.11891192,
        "type": "snoutFly",
        "spawn": "nest2",
        "checkpoints": null
      },
      {
        "count": 21,
        "delay": 0.02,
        "type": "superMosquito",
        "spawn": "nest2",
        "checkpoints": null
      },
      {
        "count": 1,
        "delay": 0.14398372,
        "type": "moth",
        "spawn": "nest2",
        "checkpoints": null
      },
      {
        "count": 6,
        "delay": 0.02,
        "type": "superMosquito",
        "spawn": "nest2",
        "checkpoints": null
      }
    ],
    [
      {
        "count": 96,
        "delay": 0.018,
        "type": "wasp",
        "spawn": "nest2",
        "checkpoints": null
      },
      {
        "count": 39,
        "delay": 0.018,
        "type": "wasp",
        "spawn": "nest1",
        "checkpoints": null
      }
    ],
    [
      {
        "count": 128,
        "delay": 0.018,
        "type": "wasp",
        "spawn": "nest1",
        "checkpoints": null
      }
    ],
    [
      {
        "count": 72,
        "delay": 0.02,
        "type": "superMosquito",
        "spawn": "nest2",
        "checkpoints": null
      },
      {
        "count": 44,
        "delay": 0.3673982,
        "type": "superMoth",
        "spawn": "nest1",
        "checkpoints": null
      },
      {
        "count": 12,
        "delay": 0.48891085,
        "type": "snoutFly",
        "spawn": "nest1",
        "checkpoints": null
      }
    ],
    [
      {
        "count": 50,
        "delay": 0.02,
        "type": "wasp",
        "spawn": "nest2",
        "checkpoints": null
      },
      {
        "count": 9,
        "delay": 0.116972566,
        "type": "snoutFly",
        "spawn": "nest1",
        "checkpoints": null
      },
      {
        "count": 12,
        "delay": 0.23041308,
        "type": "superMoth",
        "spawn": "nest2",
        "checkpoints": null
      },
      {
        "count": 26,
        "delay": 0.41534996,
        "type": "snoutFly",
        "spawn": "nest2",
        "checkpoints": null
      },
      {
        "count": 18,
        "delay": 0.02,
        "type": "superMosquito",
        "spawn": "nest1",
        "checkpoints": null
      },
      {
        "count": 9,
        "delay": 0.17652708,
        "type": "superMoth",
        "spawn": "nest1",
        "checkpoints": null
      }
    ],
    [
      {
        "count": 7,
        "delay": 0.34289348,
        "type": "snoutFly",
        "spawn": "nest2",
        "checkpoints": null
      },
      {
        "count": 91,
        "delay": 0.02,
        "type": "superMosquito",
        "spawn": "nest2",
        "checkpoints": null
      },
      {
        "count": 15,
        "delay": 0.47508538,
        "type": "moth",
        "spawn": "nest1",
        "checkpoints": null
      },
      {
        "count": 14,
        "delay": 0.02,
        "type": "superMosquito",
        "spawn": "nest2",
        "checkpoints": null
      }
    ],
    [
      {
        "count": 11,
        "delay": 0.33801335,
        "type": "snoutFly",
        "spawn": "nest1",
        "checkpoints": null
      },
      {
        "count": 41,
        "delay": 0.44733906,
        "type": "superMoth",
        "spawn": "nest2",
        "checkpoints": null
      },
      {
        "count": 11,
        "delay": 0.2517656,
        "type": "superMoth",
        "spawn": "nest2",
        "checkpoints": null
      },
      {
        "count": 17,
        "delay": 0.44197085,
        "type": "moth",
        "spawn": "nest2",
        "checkpoints": null
      },
      {
        "count": 17,
        "delay": 0.16560602,
        "type": "moth",
        "spawn": "nest1",
        "checkpoints": null
      },
      {
        "count": 10,
        "delay": 0.27294695,
        "type": "superMoth",
        "spawn": "nest1",
        "checkpoints": null
      },
      {
        "count": 28,
        "delay": 0.02,
        "type": "superMosquito",
        "spawn": "nest1",
        "checkpoints": null
      }
    ],
    [
      {
        "count": 56,
        "delay": 0.2791288,
        "type": "snoutFly",
        "spawn": "nest2",
        "checkpoints": null
      },
      {
        "count": 42,
        "delay": 0.02,
        "type": "superMosquito",
        "spawn": "nest1",
        "checkpoints": null
      },
      {
        "count": 30,
        "delay": 0.063625455,
        "type": "superMoth",
        "spawn": "nest1",
        "checkpoints": null
      },
      {
        "count": 2,
        "delay": 0.42584777,
        "type": "moth",
        "spawn": "nest1",
        "checkpoints": null
      }
    ],
    [
      {
        "count": 48,
        "delay": 0.018,
        "type": "wasp",
        "spawn": "nest2",
        "checkpoints": null
      },
      {
        "count": 98,
        "delay": 0.018,
        "type": "wasp",
        "spawn": "nest1",
        "checkpoints": null
      }
    ],
    [
      {
        "count": 58,
        "delay": 0.14103103,
        "type": "snoutFly",
        "spawn": "nest1",
        "checkpoints": null
      },
      {
        "count": 23,
        "delay": 0.35049176,
        "type": "snoutFly",
        "spawn": "nest1",
        "checkpoints": null
      },
      {
        "count": 28,
        "delay": 0.3915646,
        "type": "snoutFly",
        "spawn": "nest2",
        "checkpoints": null
      },
      {
        "count": 26,
        "delay": 0.02,
        "type": "superMosquito",
        "spawn": "nest2",
        "checkpoints": null
      },
      {
        "count": 5,
        "delay": 0.058158934,
        "type": "moth",
        "spawn": "nest1",
        "checkpoints": null
      }
    ],
    [
      {
        "count": 48,
        "delay": 0.02,
        "type": "superMosquito",
        "spawn": "nest1",
        "checkpoints": null
      },
      {
        "count": 2,
        "delay": 0.02,
        "type": "superMosquito",
        "spawn": "nest2",
        "checkpoints": null
      },
      {
        "count": 4,
        "delay": 0.42362368,
        "type": "moth",
        "spawn": "nest1",
        "checkpoints": null
      },
      {
        "count": 31,
        "delay": 0.083286464,
        "type": "snoutFly",
        "spawn": "nest1",
        "checkpoints": null
      },
      {
        "count": 50,
        "delay": 0.02,
        "type": "superMosquito",
        "spawn": "nest1",
        "checkpoints": null
      }
    ]
  ],
  "extraHardRounds": [
    5,
    7,
    9,
    14,
    15,
    17,
    22,
    24,
    33,
    35,
    40,
    41,
    47
  ],
  "bosses": []
}